fastfilters2/__init__.py
fastfilters2/_core.cpython-310-darwin.so
fastfilters2-2.0.0.dev0.dist-info/LICENSE
fastfilters2-2.0.0.dev0.dist-info/METADATA
fastfilters2-2.0.0.dev0.dist-info/WHEEL
fastfilters2-2.0.0.dev0.dist-info/top_level.txt
fastfilters2-2.0.0.dev0.dist-info/RECORD
